{
  "timestamp": 1754350839,
  "total_tokens": 2,
  "new_tokens": 0,
  "recent_tokens": 2,
  "tokens": [
    {
      "mint": "7GCihgDB8fe6KNjn2MYtkzZcRjQy3t9GHdC8uHYmW2hr",
      "symbol": "TREND",
      "name": "Trending Token",
      "created_timestamp": 1754329239,
      "market_cap": 50000,
      "price": 0.001,
      "liquidity": 100.0,
      "holders": 500,
      "is_on_pump": true,
      "source": "pump_trending"
    },
    {
      "mint": "9WzDXwBbmkg8ZTbNMqUxvQRAyrZzDsGYdLVL9zYtAWWM",
      "symbol": "HOT",
      "name": "Hot Token",
      "created_timestamp": 1754307639,
      "market_cap": 75000,
      "price": 0.002,
      "liquidity": 150.0,
      "holders": 750,
      "is_on_pump": true,
      "source": "pump_trending"
    }
  ],
  "new_tokens_list": [],
  "recent_tokens_list": [
    {
      "mint": "7GCihgDB8fe6KNjn2MYtkzZcRjQy3t9GHdC8uHYmW2hr",
      "symbol": "TREND",
      "name": "Trending Token",
      "created_timestamp": 1754329239,
      "market_cap": 50000,
      "price": 0.001,
      "liquidity": 100.0,
      "holders": 500,
      "is_on_pump": true,
      "source": "pump_trending"
    },
    {
      "mint": "9WzDXwBbmkg8ZTbNMqUxvQRAyrZzDsGYdLVL9zYtAWWM",
      "symbol": "HOT",
      "name": "Hot Token",
      "created_timestamp": 1754307639,
      "market_cap": 75000,
      "price": 0.002,
      "liquidity": 150.0,
      "holders": 750,
      "is_on_pump": true,
      "source": "pump_trending"
    }
  ],
  "filters": {
    "new_only": 0,
    "last_1_day": 2,
    "last_3_days": 2,
    "last_7_days": 2
  }
}